ikpy/__init__.py
ikpy/_version.py
ikpy/chain.py
ikpy/inverse_kinematics.py
ikpy/link.py
ikpy/logs.py
ikpy/urdf/URDF.py
ikpy/urdf/__init__.py
ikpy/urdf/utils.py
ikpy/utils/__init__.py
ikpy/utils/geometry.py
ikpy/utils/plot.py
ikpy-3.4.2.dist-info/LICENSE
ikpy-3.4.2.dist-info/METADATA
ikpy-3.4.2.dist-info/WHEEL
ikpy-3.4.2.dist-info/top_level.txt
ikpy-3.4.2.dist-info/RECORD
