Metadata-Version: 2.1
Name: ikpy
Version: 3.4.2
Summary: An inverse kinematics library aiming performance and modularity
Home-page: https://github.com/Phylliade/ikpy
Classifier: Programming Language :: Python :: 3
Classifier: Topic :: Scientific/Engineering
Provides-Extra: plot
License-File: LICENSE
